operations/__init__.py
operations/flowback.py
qep_info_objects_test-0.0.11.dist-info/METADATA
qep_info_objects_test-0.0.11.dist-info/WHEEL
qep_info_objects_test-0.0.11.dist-info/top_level.txt
qep_info_objects_test-0.0.11.dist-info/RECORD
